downsampler/__init__.py
downsampler/aggregators.py
downsampler/config.py
downsampler/core.py
downsampler/deferred.py
downsampler/edges.py
downsampler/gaps.py
downsampler/lttb.py
downsampler/utils.py
downsampler/fidelity/__init__.py
downsampler/fidelity/comparison.py
downsampler/fidelity/metrics.py
downsampler/fidelity/visualization.py
downsampler-0.1.0.dist-info/licenses/LICENSE
downsampler-0.1.0.dist-info/METADATA
downsampler-0.1.0.dist-info/WHEEL
downsampler-0.1.0.dist-info/top_level.txt
downsampler-0.1.0.dist-info/RECORD
