Metadata-Version: 2.4
Name: downsampler
Version: 0.1.0
Summary: Timeseries DataFrame downsampling with LTTB, aggregation methods, gap handling, and fidelity testing
Author-email: Eelco Doornbos <eelco.doornbos@knmi.nl>
License: MIT
Project-URL: Homepage, https://gitlab.com/KNMI-OSS/spaceweather/downsampler
Project-URL: Repository, https://gitlab.com/KNMI-OSS/spaceweather/downsampler
Keywords: timeseries,downsampling,lttb,pandas,visualization
Classifier: Development Status :: 3 - Alpha
Classifier: Intended Audience :: Science/Research
Classifier: License :: OSI Approved :: MIT License
Classifier: Programming Language :: Python :: 3
Classifier: Programming Language :: Python :: 3.10
Classifier: Programming Language :: Python :: 3.11
Classifier: Programming Language :: Python :: 3.12
Classifier: Topic :: Scientific/Engineering
Requires-Python: >=3.10
License-File: LICENSE
Requires-Dist: numpy>=1.20
Requires-Dist: pandas>=1.3
Requires-Dist: lttb>=0.3
Requires-Dist: scipy>=1.7
Provides-Extra: viz
Requires-Dist: matplotlib>=3.5; extra == "viz"
Requires-Dist: altair>=5.0; extra == "viz"
Provides-Extra: test
Requires-Dist: pytest>=7.0; extra == "test"
Requires-Dist: pytest-cov>=4.0; extra == "test"
Provides-Extra: dev
Requires-Dist: downsampler[test,viz]; extra == "dev"
Dynamic: license-file
